suriyahelloworld.py
suriyahelloworld-0.0.1.dist-info/METADATA
suriyahelloworld-0.0.1.dist-info/WHEEL
suriyahelloworld-0.0.1.dist-info/top_level.txt
suriyahelloworld-0.0.1.dist-info/RECORD
